setup.py
terminal_brackets.egg-info/PKG-INFO
terminal_brackets.egg-info/SOURCES.txt
terminal_brackets.egg-info/dependency_links.txt
terminal_brackets.egg-info/entry_points.txt
terminal_brackets.egg-info/requires.txt
terminal_brackets.egg-info/top_level.txt
terminalbrackets/__init__.py
terminalbrackets/brackets.py
terminalbrackets/cli.py