Metadata-Version: 1.0
Name: terminal-brackets
Version: 0.8
Summary: CLI application for printing out competitive brackets from provided json data
Home-page: http://github.com/Granitosaurus/terminalbracket
Author: granitosaurus
Author-email: bernardas.alisauskas@gmail.com
License: GPLv3
Platform: UNKNOWN
